sayjira/__init__.py
sayjira/sayjira.py
sayjira-0.1.2.dist-info/METADATA
sayjira-0.1.2.dist-info/WHEEL
sayjira-0.1.2.dist-info/entry_points.txt
sayjira-0.1.2.dist-info/top_level.txt
sayjira-0.1.2.dist-info/RECORD
